csvmonitor.py
csvmonitor-1.3.dist-info/LICENSE
csvmonitor-1.3.dist-info/WHEEL
csvmonitor-1.3.dist-info/METADATA
csvmonitor-1.3.dist-info/RECORD
