Metadata-Version: 2.1
Name: csvmonitor
Version: 1.3
Summary: Lightweight HTTP integration for the csvmonitor.com heartbeat service.
Author-email: "CSVMonitor.com" <support@csvmonitor.com>
Classifier: License :: OSI Approved :: MIT License
Requires-Dist: requests
Project-URL: Home, https://csvmonitor.com
